pygofastproxy/__init__.py
pygofastproxy/__main__.py
pygofastproxy/runner.py
pygofastproxy/go/config.go
pygofastproxy/go/go.mod
pygofastproxy/go/go.sum
pygofastproxy/go/proxy.go
pygofastproxy/go/ratelimit.go
pygofastproxy-1.0.8.dist-info/licenses/LICENSE
pygofastproxy-1.0.8.dist-info/METADATA
pygofastproxy-1.0.8.dist-info/WHEEL
pygofastproxy-1.0.8.dist-info/entry_points.txt
pygofastproxy-1.0.8.dist-info/top_level.txt
pygofastproxy-1.0.8.dist-info/RECORD
