Metadata-Version: 2.4
Name: pygofastproxy
Version: 1.0.8
Summary: A blazing-fast HTTP proxy for Python, powered by Go’s fasthttp library
Author: Laurent Zogaj
License-Expression: MIT
Project-URL: Homepage, https://github.com/26zl/pygofastproxy
Classifier: Programming Language :: Python :: 3
Classifier: Operating System :: OS Independent
Requires-Python: >=3.8
License-File: LICENSE
Dynamic: license-file
